statista/__init__.py
statista/confidence_interval.py
statista/descriptors.py
statista/distributions.py
statista/eva.py
statista/parameters.py
statista/plot.py
statista/sensitivity.py
statista/tools.py
statista/utils.py
statista-0.6.3.dist-info/licenses/LICENSE.md
statista-0.6.3.dist-info/METADATA
statista-0.6.3.dist-info/WHEEL
statista-0.6.3.dist-info/top_level.txt
statista-0.6.3.dist-info/RECORD
