Metadata-Version: 2.4
Name: statista
Version: 0.6.3
Summary: statistics package
Author-email: Mostafa Farrag <moah.farag@gmail.com>
License: GPL-3.0-or-later
Project-URL: Homepage, https://github.com/Serapieum-of-alex/statista
Project-URL: Documentation, https://github.com/Serapieum-of-alex/statista
Project-URL: Repository, https://github.com/Serapieum-of-alex/statista
Keywords: statistics,distributions,extreme-value-analysis,probability,sensitivity-analysis
Classifier: Development Status :: 5 - Production/Stable
Classifier: Environment :: Console
Classifier: License :: OSI Approved :: GNU General Public License v3 (GPLv3)
Classifier: Natural Language :: English
Classifier: Programming Language :: Python :: 3
Classifier: Programming Language :: Python :: 3.11
Classifier: Programming Language :: Python :: 3.12
Classifier: Programming Language :: Python :: 3.13
Classifier: Topic :: Scientific/Engineering :: GIS
Classifier: Intended Audience :: Science/Research
Classifier: Intended Audience :: Developers
Requires-Python: <4,>=3.11
License-File: LICENSE.md
Requires-Dist: numpy>=2.0.0
Requires-Dist: matplotlib>=3.9.0
Requires-Dist: pandas>=2.1.0
Requires-Dist: scikit-learn>=1.5.1
Requires-Dist: scipy>=1.14.0
Requires-Dist: loguru>=0.7.2
Provides-Extra: dev
Requires-Dist: nbval>=0.11.0; extra == "dev"
Requires-Dist: pre-commit>=3.7.1; extra == "dev"
Requires-Dist: pre-commit-hooks>=4.6.0; extra == "dev"
Requires-Dist: pytest>=8.2.2; extra == "dev"
Requires-Dist: pytest-cov>=5.0.0; extra == "dev"
Provides-Extra: docs
Requires-Dist: mkdocs>=1.5.3; extra == "docs"
Requires-Dist: mkdocs-material>=9.5.3; extra == "docs"
Requires-Dist: mkdocstrings>=0.24.0; extra == "docs"
Requires-Dist: mkdocstrings-python>=1.7.5; extra == "docs"
Requires-Dist: mike>=2.1.3; extra == "docs"
Requires-Dist: mkdocs-jupyter>=0.25.1; extra == "docs"
Requires-Dist: mkdocs-autorefs>=1.2; extra == "docs"
Requires-Dist: mkdocs-macros-plugin>=1.3.7; extra == "docs"
Requires-Dist: mkdocs-table-reader-plugin>=3.1.0; extra == "docs"
Requires-Dist: mkdocs-mermaid2-plugin>=1.2.1; extra == "docs"
Requires-Dist: jupyter-contrib-nbextensions>=0.7.0; extra == "docs"
Requires-Dist: notebook<7.0; extra == "docs"
Requires-Dist: jupyter; extra == "docs"
Dynamic: license-file
